LICENSE
MANIFEST.in
README.rst
VERSION
requirements.txt
setup.py
mwevents/__init__.py
mwevents/configuration.py
mwevents/defaults.py
mwevents/util.py
mwevents.egg-info/PKG-INFO
mwevents.egg-info/SOURCES.txt
mwevents.egg-info/dependency_links.txt
mwevents.egg-info/requires.txt
mwevents.egg-info/top_level.txt
mwevents/sources/__init__.py
mwevents/sources/api.py
mwevents/sources/database.py
mwevents/sources/source.py
mwevents/types/__init__.py
mwevents/types/block.py
mwevents/types/page.py
mwevents/types/protection.py
mwevents/types/revision.py
mwevents/types/state_marker.py
mwevents/types/timestamp.py
mwevents/types/unavailable.py
mwevents/types/user.py
mwevents/types/events/__init__.py
mwevents/types/events/event.py
mwevents/types/events/match.py
mwevents/types/events/page_created.py
mwevents/types/events/page_deleted.py
mwevents/types/events/page_moved.py
mwevents/types/events/page_protection_modified.py
mwevents/types/events/page_restored.py
mwevents/types/events/revision_saved.py
mwevents/types/events/revisions_deleted.py
mwevents/types/events/user_blocked.py
mwevents/types/events/user_groups_modified.py
mwevents/types/events/user_registered.py
mwevents/types/events/user_renamed.py
mwevents/types/events/user_unblocked.py
mwevents/types/events/tests/__init__.py
mwevents/types/events/tests/test_event.py
mwevents/types/events/tests/test_page_restored.py
mwevents/types/events/tests/test_revision_saved.py
mwevents/types/tests/__init__.py
mwevents/types/tests/test_block.py
mwevents/types/tests/test_page.py
mwevents/types/tests/test_protection.py
mwevents/types/tests/test_revision.py
mwevents/types/tests/test_state_marker.py
mwevents/types/tests/test_timestamp.py
mwevents/types/tests/test_unavailable.py
mwevents/types/tests/test_user.py