Metadata-Version: 1.1
Name: mwevents
Version: 0.1.0
Summary: Standardized public MediaWiki events for tools and Science.
Home-page: http://pypi.python.org/pypi/mwevents
Author: Aaron Halfaker
Author-email: aaron.halfaker@gmail.com
License: The MIT License (MIT)
